MANIFEST.in
README.rst
setup.py
flasky_settings/__init__.py
flasky_settings/error.py
flasky_settings/main.py
flasky_settings.egg-info/PKG-INFO
flasky_settings.egg-info/SOURCES.txt
flasky_settings.egg-info/dependency_links.txt
flasky_settings.egg-info/not-zip-safe
flasky_settings.egg-info/requires.txt
flasky_settings.egg-info/top_level.txt
flasky_settings/elements/__init__.py
flasky_settings/forms/__init__.py
flasky_settings/forms/settings_form.py
flasky_settings/settings/__init__.py
flasky_settings/settings/settings_class.py
flasky_settings/settings/settings_element.py
flasky_settings/settings/settings_item.py
flasky_settings/settings/settings_page.py
flasky_settings/settings/settings_property.py
flasky_settings/static/.DS_Store
flasky_settings/static/css/style.css
flasky_settings/static/js/form.js
flasky_settings/static/js/init.js
flasky_settings/static/js/settings.js
flasky_settings/static/js/utils/element_parser.js
flasky_settings/static/js/utils/settings_manager.js
flasky_settings/templates/.DS_Store
flasky_settings/templates/flasky_settings/settings_group.html
flasky_settings/templates/flasky_settings/settings_page.html
flasky_settings/templates/flasky_settings/elements/js.html
flasky_settings/templates/flasky_settings/elements/meta.html
flasky_settings/templates/flasky_settings/forms/alternativ_1.html
flasky_settings/templates/flasky_settings/forms/default.html
flasky_settings/templates/flasky_settings/macros/settings_form.html
flasky_settings/templates/flasky_settings/setting/bool.html
flasky_settings/templates/flasky_settings/setting/datetime.html
flasky_settings/templates/flasky_settings/setting/default.html
flasky_settings/templates/flasky_settings/setting/multi_select_as_list.html
flasky_settings/templates/flasky_settings/setting/select.html
flasky_settings/templates/flasky_settings/setting/string.html
flasky_settings/templates/flasky_settings/setting/text.html
flasky_settings/templates/flasky_settings/setting/sub/title_div.html