Metadata-Version: 2.1
Name: flasky-settings
Version: 0.0.2.2
Summary: Flask extension that includes a Settings-Manager in your project
Home-page: https://github.com/LordBex/flasky-settings
Author: lordbex
Author-email: lordibex@protonmail.com
License: UNKNOWN
Platform: any
Classifier: Environment :: Web Environment
Classifier: Intended Audience :: Developers
Classifier: Operating System :: OS Independent
Classifier: Programming Language :: Python
Classifier: Programming Language :: Python :: 3.10
Classifier: Topic :: Internet :: WWW/HTTP :: Dynamic Content
Classifier: Topic :: Software Development :: Libraries :: Python Modules
